{
       "info": {
        "url_png_icon_64x64": "http://staykpool.com/wp-content/uploads/2021/04/Stayk_Antraciet_Icon_64x64.jpg",
        "location": "Den Haag, The Netherlands",
        "social": {
            "reddit_handle": "u/STAYK_Pool/",
            "twitter_handle": "STAYKPool",
            "facebook_handle": "https://www.facebook.com/StaykPool",
            "github_handle": "BaasMons"
        },
        "about": {
            "me": "Single Pool Operator",
            "server": "1x Cloudbased Block producer, 2x Bare Metal relays and 1 x Cloud relay"
    },
    "my-pool-ids": {
        "0": "fd6049e6058460efa683a0e090e5b98d0ea1d6db539a5a9b0bc649de"
    },
    "when-satured-then-recommend": {
        "0": "Any F2LB Pool - support decentralization"
    }
}
}
